gmail_mcp_server/__init__.py
gmail_mcp_server/server.py
gmail_mcp_server-0.1.1.dist-info/METADATA
gmail_mcp_server-0.1.1.dist-info/WHEEL
gmail_mcp_server-0.1.1.dist-info/entry_points.txt
gmail_mcp_server-0.1.1.dist-info/licenses/LICENSE
gmail_mcp_server-0.1.1.dist-info/RECORD
