Metadata-Version: 2.4
Name: gmail-mcp-server
Version: 0.1.1
Summary: A Python MCP server for Gmail and Google Calendar integration with Claude Desktop
Project-URL: Homepage, https://github.com/aniket-raskar1/my-gmail-mcp-server
Project-URL: Repository, https://github.com/aniket-raskar1/my-gmail-mcp-server
Project-URL: Documentation, https://github.com/aniket-raskar1/my-gmail-mcp-server/blob/main/README.md
Project-URL: Issues, https://github.com/aniket-raskar1/my-gmail-mcp-server/issues
Author-email: Aniket <aniketraskar932@gmail.com>
License: MIT License
License-File: LICENSE
Keywords: automation,calendar,claude,email,gmail,google-calendar,mcp
Requires-Python: >=3.8
Requires-Dist: google-api-python-client>=2.0.0
Requires-Dist: google-auth-oauthlib>=0.4.0
Requires-Dist: mcp>=0.1.0
Requires-Dist: schedule>=1.1.0
